carry_in_adder.sv
module carry_in_adder (
    input logic A,
    input logic B,
    input logic Cin,
    output logic S,
    output logic Cout
);

assign S = A ^ B ^ Cin;
assign Cout = (A & B) | (A & Cin) | (B & Cin);

endmodule

ripple_adder_4bit.sv
module ripple_adder_4bit (
    input logic [3:0] A,
    input logic [3:0] B,
    output logic [3:0] S,
    output logic Cout
);

logic c0, c1, c2;

carry_in_adder a0 (.A(A[0]), .B(B[0]), .Cin(1'b0), .S(S[0]), .Cout(c0));
carry_in_adder a1 (.A(A[1]), .B(B[1]), .Cin(c0), .S(S[1]), .Cout(c1));
carry_in_adder a2 (.A(A[2]), .B(B[2]), .Cin(c1), .S(S[2]), .Cout(c2));
carry_in_adder a3 (.A(A[3]), .B(B[3]), .Cin(c2), .S(S[3]), .Cout(Cout));

endmodule

accumulator.sv
module accumulator (
    input logic clk,
    input logic [3:0] A,
    output logic [5:0] S,
    output logic overflow
);

logic c0, c1, ovfl;
logic [5:0] sum;

ripple_adder_4bit ra (.A(A), .B(S[3:0]), .S(sum[3:0]), .Cout(c0));
carry_in_adder ca0 (.A(c0), .B(S[4]), .Cin(1'b0), .S(sum[4]), .Cout(c1));
carry_in_adder ca1 (.A(c1), .B(S[5]), .Cin(1'b0), .S(sum[5]), .Cout(ovfl));

always_ff @(posedge clk) begin
    S = sum;
    if (overflow == 1) overflow = 1;
    else overflow = ovfl;
end

endmodule

accumulator.vcd
$version Generated by VerilatedVcd $end
$timescale 1ps $end
 $scope module TOP $end
  $var wire 1 + clk $end
  $var wire 4 , A [3:0] $end
  $var wire 6 - S [5:0] $end
  $var wire 1 . overflow $end
  $scope module accumulator $end
   $var wire 1 + clk $end
   $var wire 4 , A [3:0] $end
   $var wire 6 - S [5:0] $end
   $var wire 1 . overflow $end
   $var wire 1 " c0 $end
   $var wire 1 / c1 $end
   $var wire 1 0 ovfl $end
   $var wire 6 1 sum [5:0] $end
   $scope module ca0 $end
    $var wire 1 " A $end
    $var wire 1 2 B $end
    $var wire 1 ? Cin $end
    $var wire 1 3 S $end
    $var wire 1 / Cout $end
   $upscope $end
   $scope module ca1 $end
    $var wire 1 / A $end
    $var wire 1 4 B $end
    $var wire 1 ? Cin $end
    $var wire 1 5 S $end
    $var wire 1 0 Cout $end
   $upscope $end
   $scope module ra $end
    $var wire 4 , A [3:0] $end
    $var wire 4 6 B [3:0] $end
    $var wire 4 # S [3:0] $end
    $var wire 1 " Cout $end
    $var wire 1 $ c0 $end
    $var wire 1 % c1 $end
    $var wire 1 & c2 $end
    $scope module a0 $end
     $var wire 1 7 A $end
     $var wire 1 8 B $end
     $var wire 1 ? Cin $end
     $var wire 1 ' S $end
     $var wire 1 $ Cout $end
    $upscope $end
    $scope module a1 $end
     $var wire 1 9 A $end
     $var wire 1 : B $end
     $var wire 1 $ Cin $end
     $var wire 1 ( S $end
     $var wire 1 % Cout $end
    $upscope $end
    $scope module a2 $end
     $var wire 1 ; A $end
     $var wire 1 < B $end
     $var wire 1 % Cin $end
     $var wire 1 ) S $end
     $var wire 1 & Cout $end
    $upscope $end
    $scope module a3 $end
     $var wire 1 = A $end
     $var wire 1 > B $end
     $var wire 1 & Cin $end
     $var wire 1 * S $end
     $var wire 1 " Cout $end
    $upscope $end
   $upscope $end
  $upscope $end
 $upscope $end
$enddefinitions $end


#0
0"
b0000 #
0$
0%
0&
0'
0(
0)
0*
0+
b0000 ,
b000000 -
0.
0/
00
b000000 1
02
03
04
05
b0000 6
07
08
09
0:
0;
0<
0=
0>
0?
#1
1+
#2
b1100 #
1)
1*
0+
b1100 ,
b001100 1
1;
1=
#3
1"
b1000 #
1&
0)
1+
b001100 -
b011000 1
13
b1100 6
1<
1>
#4
b0000 #
0*
0+
b0100 ,
b010000 1
0=
#5
0"
b0100 #
0&
1)
1+
b010000 -
b010100 1
12
b0000 6
0<
0>
#6
b1011 #
1'
1(
0)
1*
0+
b1011 ,
b011011 1
17
19
0;
1=
#7
1"
b0110 #
1$
1%
0'
1)
0*
1+
b011011 -
1/
b100110 1
03
15
b1011 6
18
1:
1>
#8
0"
b1101 #
0$
1'
0(
1*
0+
b0010 ,
0/
b011101 1
13
05
07
0=
#9
b1111 #
0%
1(
1+
b011101 -
b011111 1
b1101 6
0:
1<
#10
0+
#11
1"
b0001 #
1%
1&
0(
0)
0*
1+
b011111 -
1/
b100001 1
03
15
b1111 6
1:
#12
0+
#13
0"
b0011 #
0%
0&
1(
1+
b100001 -
0/
b100011 1
02
14
b0001 6
0:
0<
0>
#14
b0010 #
1$
0'
0+
b0001 ,
b100010 1
17
09
#15
b0011 #
0$
1'
1+
b100010 -
b100011 1
b0010 6
08
1:
#16
b1011 #
1*
0+
b1001 ,
b101011 1
1=
#17
1"
b0100 #
1$
1%
0'
0(
1)
0*
1+
b101011 -
b110100 1
13
b1011 6
18
1>
#18
b0000 #
1&
0)
0+
b0101 ,
b110000 1
1;
0=
#19
0"
b0101 #
0$
0%
0&
1'
1)
1+
b110000 -
b110101 1
12
b0000 6
08
0:
0>
